nvfuser/_C.cpython-312-x86_64-linux-gnu.so
nvfuser/__init__.py
nvfuser/__init__.pyi
nvfuser/benchmark_utils.py
nvfuser/nvfuser_version.py
nvfuser/pytorch_utils.py
nvfuser/version.py
nvfuser/contrib/__init__.py
nvfuser/contrib/nn/__init__.py
nvfuser/contrib/nn/normalization.py
nvfuser_common/__init__.py
nvfuser_common/utils.py
nvfuser_common/include/nvfuser/alias_analysis.h
nvfuser_common/include/nvfuser/bfs.h
nvfuser_common/include/nvfuser/codegen.h
nvfuser_common/include/nvfuser/compute_at.h
nvfuser_common/include/nvfuser/compute_at_map.h
nvfuser_common/include/nvfuser/contiguity.h
nvfuser_common/include/nvfuser/cuda_utils.h
nvfuser_common/include/nvfuser/debug.h
nvfuser_common/include/nvfuser/disjoint_set.h
nvfuser_common/include/nvfuser/dispatch.h
nvfuser_common/include/nvfuser/driver_api.h
nvfuser_common/include/nvfuser/dynamic_transform.h
nvfuser_common/include/nvfuser/evaluator_common.h
nvfuser_common/include/nvfuser/exceptions.h
nvfuser_common/include/nvfuser/expr_evaluator.h
nvfuser_common/include/nvfuser/expr_simplifier.h
nvfuser_common/include/nvfuser/fusion.h
nvfuser_common/include/nvfuser/fusion_guard.h
nvfuser_common/include/nvfuser/fusion_profiler.h
nvfuser_common/include/nvfuser/fusion_segmenter.h
nvfuser_common/include/nvfuser/global_allocator.h
nvfuser_common/include/nvfuser/graph_traversal.h
nvfuser_common/include/nvfuser/grouped_reduction.h
nvfuser_common/include/nvfuser/index_compute.h
nvfuser_common/include/nvfuser/instrumentation.h
nvfuser_common/include/nvfuser/interval_analysis.h
nvfuser_common/include/nvfuser/iter_visitor.h
nvfuser_common/include/nvfuser/kernel.h
nvfuser_common/include/nvfuser/kernel_ir.h
nvfuser_common/include/nvfuser/kernel_ir_dispatch.h
nvfuser_common/include/nvfuser/linked_hash_map.h
nvfuser_common/include/nvfuser/logical_domain_map.h
nvfuser_common/include/nvfuser/macros.h
nvfuser_common/include/nvfuser/mma_type.h
nvfuser_common/include/nvfuser/opaque_type.h
nvfuser_cu128_torch29-0.2.35.dev20260115.dist-info/METADATA
nvfuser_cu128_torch29-0.2.35.dev20260115.dist-info/WHEEL
nvfuser_cu128_torch29-0.2.35.dev20260115.dist-info/top_level.txt
nvfuser_cu128_torch29-0.2.35.dev20260115.dist-info/RECORD
nvfuser_cu128_torch29-0.2.35.dev20260115.dist-info/licenses/LICENSE
